anycache-2.4.0.dist-info/METADATA
anycache-2.4.0.dist-info/WHEEL
anycache-2.4.0.dist-info/entry_points.txt
anycache-2.4.0.dist-info/licenses/LICENSE
anycache/__init__.py
anycache-2.4.0.dist-info/RECORD
