Metadata-Version: 2.4
Name: anycache
Version: 2.4.0
Summary: Cache any python object to file using improved pickling
Keywords: cache,caching,cache file,pickle,dill
Author-Email: Daniel Jakschik <c0fec0de@gmail.com>
License-Expression: MIT
Classifier: Topic :: Software Development :: Libraries :: Python Modules
Classifier: Development Status :: 5 - Production/Stable
Classifier: Programming Language :: Python :: 3
Classifier: Programming Language :: Python :: 3.9
Classifier: Programming Language :: Python :: 3.10
Classifier: Programming Language :: Python :: 3.11
Classifier: Programming Language :: Python :: 3.12
Classifier: Programming Language :: Python :: 3.13
Classifier: Operating System :: OS Independent
Project-URL: Homepage, https://github.com/c0fec0de/anycache
Project-URL: Documentation, https://anycache.readthedocs.io/en/stable/
Project-URL: Bug Tracker, https://github.com/c0fec0de/anycache/issues
Requires-Python: <4.0,>=3.9.0
Requires-Dist: dill>=0.3.7
Requires-Dist: filelock>=3.13.0
